{
	"analysisDataInfo": [{
		"devCode": "862033031901372",
		"timeLength": 1802411
	}, {
		"devCode": "866413038107288",
		"timeLength": 2232
	}, {
		"devCode": "867392033225361",
		"timeLength": 88
	}, {
		"devCode": "867392034516867",
		"timeLength": 28424
	}, {
		"devCode": "867830020677847",
		"timeLength": 1012
	}, {
		"devCode": "BBCD001_10092",
		"timeLength": 119876
	}, {
		"devCode": "BBCD001_90186",
		"timeLength": 2044466
	}, {
		"devCode": "BBCG001_00402",
		"timeLength": 28680
	}, {
		"devCode": "BBCG402_10087",
		"timeLength": 919440
	}, {
		"devCode": "BBCG403_10099",
		"timeLength": 949459
	}, {
		"devCode": "BBCH001_30085",
		"timeLength": 9937
	}, {
		"devCode": "BBCH001_80153",
		"timeLength": 142460
	}, {
		"devCode": "JT400C001-H_00075",
		"timeLength": 2998715
	}, {
		"devCode": "JT400C001-H_00190",
		"timeLength": 2044654
	}, {
		"devCode": "JT400C001-H_20056",
		"timeLength": 4471
	}, {
		"devCode": "JT400C001-H_40100",
		"timeLength": 4823508
	}, {
		"devCode": "test",
		"timeLength": 375743
	}],
	"retcode": 1
}